<?xml version="1.0" encoding="utf-8"?>
<LanguageData>
  <HaulingUrgent.labelShort>Haul+</HaulingUrgent.labelShort>
  <HaulingUrgent.pawnLabel>Urgent hauler</HaulingUrgent.pawnLabel>
  <HaulingUrgent.gerundLabel>Hauling urgently</HaulingUrgent.gerundLabel>
  <HaulingUrgent.description>High-priority hauling. Works like the regular kind, but only for things that are manually designated. Use &lt;b>Architect > Orders > Haul Urgently&lt;/b> to designate things to haul.\nAdded by the Allow Tool mod. Can be disabled in Options > Mod Settings.</HaulingUrgent.description>
  <HaulingUrgent.verb>Haul urgently</HaulingUrgent.verb>
  <FinishingOff.labelShort>Finish</FinishingOff.labelShort>
  <FinishingOff.pawnLabel>Executor</FinishingOff.pawnLabel>
  <FinishingOff.gerundLabel>Finishing off</FinishingOff.gerundLabel>
  <FinishingOff.description>Quickly and painlessly kill downed creatures.\nAdded by the Allow Tool mod. Can be disabled in Options > Mod Settings.</FinishingOff.description>
  <FinishingOff.verb>Finish off</FinishingOff.verb>
</LanguageData>