<?xml version="1.0" encoding="UTF-8"?>
<LanguageData>
  <Brazier.label>brazier</Brazier.label>
  <Brazier.description>A bowl-shaped furnishing used to hold a fire. Will light the surroundings and create heat.</Brazier.description>
  
  <Drape.label>drape</Drape.label>
  <Drape.description>A decorative sheet hanging from a vertical wooden frame. Appropriate for royal rooms.</Drape.description>
  
  <GrandThrone.label>grand meditation throne</GrandThrone.label>
  <GrandThrone.description>A massive, ornate chair, designed for a dignity-focused psycaster to sit and meditate. Reigning on a throne is a form of meditation that builds up psyfocus. For dignity psycasters, more impressive meditation thrones and thronerooms increase the rate of psyfocus gain.</GrandThrone.description>
  
  <Throne.label>meditation throne</Throne.label>
  <Throne.description>A large, ornate chair designed for a dignity-focused psycaster to sit and meditate. Reigning on a throne is a form of meditation that builds up psyfocus. For dignity psycasters, more impressive meditation thrones and thronerooms increase the rate of psyfocus gain.</Throne.description>
</LanguageData>