<?xml version="1.0" encoding="UTF-8"?>
<LanguageData>
  <BulletShieldPsychic.label>skipshield</BulletShieldPsychic.label>
  
  <Flashstorm.label>flashstorm</Flashstorm.label>
  
  <MonumentMarker.label>monument marker</MonumentMarker.label>
  <MonumentMarker.description>Marks the place where you intend to build a monument. Once placed, this cannot be moved.</MonumentMarker.description>
  
  <PawnJumper.label>flying</PawnJumper.label>
  
  <SolarPinhole.label>solar pinhole</SolarPinhole.label>
</LanguageData>