<?xml version="1.0" encoding="utf-8"?>
<LanguageData>
  <LeaderTitleMaker_RH2GruppaKrovi.rulePack.rulesStrings.0>r_leaderTitle->komandir</LeaderTitleMaker_RH2GruppaKrovi.rulePack.rulesStrings.0>
  <RH2NamerIdeo_GruppaKrovi.rulePack.rulesStrings.0>r_ideoName->[GKAdjective] communism</RH2NamerIdeo_GruppaKrovi.rulePack.rulesStrings.0>
  <RH2NamerIdeo_GruppaKrovi.rulePack.rulesStrings.1>r_memberName->comrade</RH2NamerIdeo_GruppaKrovi.rulePack.rulesStrings.1>
  <RH2NamerIdeo_GruppaKrovi.rulePack.rulesStrings.2>r_memberName->communist</RH2NamerIdeo_GruppaKrovi.rulePack.rulesStrings.2>
  <RH2NamerIdeo_GruppaKrovi.rulePack.rulesStrings.3>r_memberName->socialist</RH2NamerIdeo_GruppaKrovi.rulePack.rulesStrings.3>
  <RH2NamerIdeo_GruppaKrovi.rulePack.rulesStrings.4>r_memberName->soviet</RH2NamerIdeo_GruppaKrovi.rulePack.rulesStrings.4>
  <RH2NamerIdeo_GruppaKrovi.rulePack.rulesStrings.5>r_ideoAdjective(priority=1)->soviet</RH2NamerIdeo_GruppaKrovi.rulePack.rulesStrings.5>
  <RH2NamerIdeo_GruppaKrovi.rulePack.rulesStrings.6>creed->[genericCreed]</RH2NamerIdeo_GruppaKrovi.rulePack.rulesStrings.6>
  <RH2NamerIdeo_GruppaKrovi.rulePack.rulesStrings.7>genericCreed->creed</RH2NamerIdeo_GruppaKrovi.rulePack.rulesStrings.7>
  <RH2NamerIdeo_GruppaKrovi.rulePack.rulesStrings.8>genericCreed->doctrine</RH2NamerIdeo_GruppaKrovi.rulePack.rulesStrings.8>
  <RH2NamerIdeo_GruppaKrovi.rulePack.rulesStrings.9>genericCreed->way</RH2NamerIdeo_GruppaKrovi.rulePack.rulesStrings.9>
  <RH2NamerIdeo_GruppaKrovi.rulePack.rulesStrings.10>genericCreed->path</RH2NamerIdeo_GruppaKrovi.rulePack.rulesStrings.10>
  <RH2NamerIdeo_GruppaKrovi.rulePack.rulesStrings.11>GKAdjective->neo</RH2NamerIdeo_GruppaKrovi.rulePack.rulesStrings.11>
  <RH2NamerIdeo_GruppaKrovi.rulePack.rulesStrings.12>GKAdjective->federation</RH2NamerIdeo_GruppaKrovi.rulePack.rulesStrings.12>
  <RH2NamerIdeo_GruppaKrovi.rulePack.rulesStrings.13>GKAdjective->nova</RH2NamerIdeo_GruppaKrovi.rulePack.rulesStrings.13>
  <RH2NamerIdeo_GruppaKrovi.rulePack.rulesStrings.14>GKAdjective->neo soviet</RH2NamerIdeo_GruppaKrovi.rulePack.rulesStrings.14>
  <RH2NamerIdeo_GruppaKrovi.rulePack.rulesStrings.15>GKAdjective->united</RH2NamerIdeo_GruppaKrovi.rulePack.rulesStrings.15>
  <RH_NamerGruppaKroviOutposts.rulePack.rulesStrings.0>name->Avanpost [RH_GruppaKroviCallsignNumber][RH_GruppaKroviCallsignNumber]</RH_NamerGruppaKroviOutposts.rulePack.rulesStrings.0>
  <RH_NamerGruppaKroviOutposts.rulePack.rulesStrings.1>name->[RH_GruppaKroviCallsigns] [RH_GruppaKroviCallsignNumber][RH_GruppaKroviCallsignNumber][RH_GruppaKroviCallsignNumber]</RH_NamerGruppaKroviOutposts.rulePack.rulesStrings.1>
  <RH_NamerGruppaKroviOutposts.rulePack.rulesStrings.2>name->[RH_GruppaKroviCallsigns] [RH_GruppaKroviCallsignNumber][RH_GruppaKroviCallsignNumber]</RH_NamerGruppaKroviOutposts.rulePack.rulesStrings.2>
  <RH_NamerGruppaKroviOutposts.rulePack.rulesStrings.3>name->[RH_GruppaKroviBaseGen]</RH_NamerGruppaKroviOutposts.rulePack.rulesStrings.3>
  <RH2_NamerPerson_Soviet.rulePack.rulesStrings.0>r_name(p=3)->[RH_SovietMales] [RH_SovietSurname]</RH2_NamerPerson_Soviet.rulePack.rulesStrings.0>
  <RH2_NamerPerson_Soviet.rulePack.rulesStrings.1>r_name(p=3)->[RH_SovietMales] '[RH_SovietNicknames]' [RH_SovietSurname]</RH2_NamerPerson_Soviet.rulePack.rulesStrings.1>
  <RH2_NamerPerson_Soviet.rulePack.rulesStrings.2>r_name(p=3)->[RH_SovietMales] [RH_SovietSurname]</RH2_NamerPerson_Soviet.rulePack.rulesStrings.2>
  <RH2_NamerPerson_SovietFemale.rulePack.rulesStrings.0>r_name(p=3)->[RH_SovietFemales] [RH_SovietSurname]</RH2_NamerPerson_SovietFemale.rulePack.rulesStrings.0>
  <RH2_NamerPerson_SovietFemale.rulePack.rulesStrings.1>r_name(p=3)->[RH_SovietFemales] '[RH_SovietNicknames]' [RH_SovietSurname]</RH2_NamerPerson_SovietFemale.rulePack.rulesStrings.1>
  <RH2_NamerPerson_SovietFemale.rulePack.rulesStrings.2>r_name(p=3)->[RH_SovietFemales] [RH_SovietSurname]</RH2_NamerPerson_SovietFemale.rulePack.rulesStrings.2>
</LanguageData>