<?xml version="1.0" encoding="utf-8"?>
<LanguageData>
  <AA_AnimalResource.label>gather animal resource</AA_AnimalResource.label>
  <AA_AnimalResource.verb>gather animal resource from</AA_AnimalResource.verb>
  <AA_AnimalResource.gerund>gathering animal resource from</AA_AnimalResource.gerund>
  <AA_WorkGiverDestroyItem.label>destroy item</AA_WorkGiverDestroyItem.label>
  <AA_WorkGiverDestroyItem.verb>destroy</AA_WorkGiverDestroyItem.verb>
  <AA_WorkGiverDestroyItem.gerund>destroying</AA_WorkGiverDestroyItem.gerund>
</LanguageData>